<annotation>
	<folder>JPEGImages_SR</folder>
	<filename>Atopic_dermatitis_1_96_BSRGANx2.jpg</filename>
	<path>C:\Users\ASUS\Desktop\data\VOCdevkit\VOC2007\JPEGImages_SR\Atopic_dermatitis_1_96_BSRGANx2.jpg</path>
	<source>
		<database>Unknown</database>
	</source>
	<size>
		<width>936</width>
		<height>526</height>
		<depth>3</depth>
	</size>
	<segmented>0</segmented>
	<object>
		<name>Atopic dermatitis</name>
		<pose>Unspecified</pose>
		<truncated>0</truncated>
		<difficult>0</difficult>
		<bndbox>
			<xmin>188</xmin>
			<ymin>7</ymin>
			<xmax>695</xmax>
			<ymax>487</ymax>
		</bndbox>
	</object>
	<object>
		<name>Atopic dermatitis</name>
		<pose>Unspecified</pose>
		<truncated>0</truncated>
		<difficult>0</difficult>
		<bndbox>
			<xmin>704</xmin>
			<ymin>15</ymin>
			<xmax>928</xmax>
			<ymax>194</ymax>
		</bndbox>
	</object>
</annotation>
