<?xml version="1.0" ?><annotation>
	<folder>Chickenpox</folder>
	<filename>Chickenpox_124.jpg</filename>
	<path>C:\Users\fdd2013326601001\Desktop\Images\Chickenpox\Chickenpox_124.jpg</path>
	<source>
		<database>Unknown</database>
	</source>
	<size>
		<width>900</width>
		<height>600</height>
		<depth>3</depth>
	</size>
	<segmented>0</segmented>
	<object>
		<name>Chickenpox</name>
		<pose>Unspecified</pose>
		<truncated>0</truncated>
		<difficult>0</difficult>
		<bndbox>
			<xmin>548</xmin>
			<ymin>398</ymin>
			<xmax>614</xmax>
			<ymax>458</ymax>
		</bndbox>
	</object>
</annotation>