<annotation>
	<folder>222</folder>
	<filename>Diaper_dermatitis_22_BSRGANx2_USM_sharpen_rotate6.jpg</filename>
	<path>C:\Users\fdd2013326601001\Desktop\222\Diaper_dermatitis_22_BSRGANx2_USM_sharpen_rotate6.jpg</path>
	<source>
		<database>Unknown</database>
	</source>
	<size>
		<width>544</width>
		<height>370</height>
		<depth>3</depth>
	</size>
	<segmented>0</segmented>
	<object>
		<name>Diaper dermatitis</name>
		<pose>Unspecified</pose>
		<truncated>1</truncated>
		<difficult>0</difficult>
		<bndbox>
			<xmin>62</xmin>
			<ymin>1</ymin>
			<xmax>444</xmax>
			<ymax>370</ymax>
		</bndbox>
	</object>
</annotation>
