<?xml version="1.0" ?><annotation>
	<folder>Diaper_dermatitis</folder>
	<filename>Diaper_dermatitis_29.jpg</filename>
	<path>C:\Users\ASUS\Desktop\model\images(2022.05.08)\Diaper_dermatitis\Diaper_dermatitis_29.jpg</path>
	<source>
		<database>Unknown</database>
	</source>
	<size>
		<width>550</width>
		<height>366</height>
		<depth>3</depth>
	</size>
	<segmented>0</segmented>
	<object>
		<name>Diaper dermatitis</name>
		<pose>Unspecified</pose>
		<truncated>0</truncated>
		<difficult>0</difficult>
		<bndbox>
			<xmin>40</xmin>
			<ymin>40</ymin>
			<xmax>516</xmax>
			<ymax>338</ymax>
		</bndbox>
	</object>
</annotation>