<?xml version="1.0" ?><annotation>
	<folder>furuncle</folder>
	<filename>furuncle_80.jpg</filename>
	<path>C:\Users\ASUS\Desktop\images\furuncle\furuncle_80.jpg</path>
	<source>
		<database>Unknown</database>
	</source>
	<size>
		<width>1036</width>
		<height>776</height>
		<depth>3</depth>
	</size>
	<segmented>0</segmented>
	<object>
		<name>furuncle</name>
		<pose>Unspecified</pose>
		<truncated>0</truncated>
		<difficult>0</difficult>
		<bndbox>
			<xmin>168</xmin>
			<ymin>248</ymin>
			<xmax>228</xmax>
			<ymax>312</ymax>
		</bndbox>
	</object>
	<object>
		<name>furuncle</name>
		<pose>Unspecified</pose>
		<truncated>0</truncated>
		<difficult>0</difficult>
		<bndbox>
			<xmin>136</xmin>
			<ymin>364</ymin>
			<xmax>192</xmax>
			<ymax>436</ymax>
		</bndbox>
	</object>
	<object>
		<name>furuncle</name>
		<pose>Unspecified</pose>
		<truncated>0</truncated>
		<difficult>0</difficult>
		<bndbox>
			<xmin>428</xmin>
			<ymin>616</ymin>
			<xmax>500</xmax>
			<ymax>684</ymax>
		</bndbox>
	</object>
	<object>
		<name>furuncle</name>
		<pose>Unspecified</pose>
		<truncated>0</truncated>
		<difficult>0</difficult>
		<bndbox>
			<xmin>200</xmin>
			<ymin>692</ymin>
			<xmax>296</xmax>
			<ymax>760</ymax>
		</bndbox>
	</object>
	<object>
		<name>furuncle</name>
		<pose>Unspecified</pose>
		<truncated>0</truncated>
		<difficult>0</difficult>
		<bndbox>
			<xmin>660</xmin>
			<ymin>632</ymin>
			<xmax>716</xmax>
			<ymax>692</ymax>
		</bndbox>
	</object>
	<object>
		<name>furuncle</name>
		<pose>Unspecified</pose>
		<truncated>0</truncated>
		<difficult>0</difficult>
		<bndbox>
			<xmin>468</xmin>
			<ymin>568</ymin>
			<xmax>536</xmax>
			<ymax>612</ymax>
		</bndbox>
	</object>
	<object>
		<name>furuncle</name>
		<pose>Unspecified</pose>
		<truncated>0</truncated>
		<difficult>0</difficult>
		<bndbox>
			<xmin>316</xmin>
			<ymin>112</ymin>
			<xmax>380</xmax>
			<ymax>176</ymax>
		</bndbox>
	</object>
	<object>
		<name>furuncle</name>
		<pose>Unspecified</pose>
		<truncated>0</truncated>
		<difficult>0</difficult>
		<bndbox>
			<xmin>228</xmin>
			<ymin>180</ymin>
			<xmax>272</xmax>
			<ymax>224</ymax>
		</bndbox>
	</object>
	<object>
		<name>furuncle</name>
		<pose>Unspecified</pose>
		<truncated>0</truncated>
		<difficult>0</difficult>
		<bndbox>
			<xmin>276</xmin>
			<ymin>316</ymin>
			<xmax>316</xmax>
			<ymax>352</ymax>
		</bndbox>
	</object>
	<object>
		<name>furuncle</name>
		<pose>Unspecified</pose>
		<truncated>0</truncated>
		<difficult>0</difficult>
		<bndbox>
			<xmin>340</xmin>
			<ymin>280</ymin>
			<xmax>424</xmax>
			<ymax>348</ymax>
		</bndbox>
	</object>
	<object>
		<name>furuncle</name>
		<pose>Unspecified</pose>
		<truncated>0</truncated>
		<difficult>0</difficult>
		<bndbox>
			<xmin>332</xmin>
			<ymin>380</ymin>
			<xmax>384</xmax>
			<ymax>420</ymax>
		</bndbox>
	</object>
	<object>
		<name>furuncle</name>
		<pose>Unspecified</pose>
		<truncated>0</truncated>
		<difficult>0</difficult>
		<bndbox>
			<xmin>540</xmin>
			<ymin>324</ymin>
			<xmax>592</xmax>
			<ymax>372</ymax>
		</bndbox>
	</object>
	<object>
		<name>furuncle</name>
		<pose>Unspecified</pose>
		<truncated>0</truncated>
		<difficult>0</difficult>
		<bndbox>
			<xmin>640</xmin>
			<ymin>380</ymin>
			<xmax>680</xmax>
			<ymax>420</ymax>
		</bndbox>
	</object>
	<object>
		<name>furuncle</name>
		<pose>Unspecified</pose>
		<truncated>0</truncated>
		<difficult>0</difficult>
		<bndbox>
			<xmin>636</xmin>
			<ymin>236</ymin>
			<xmax>680</xmax>
			<ymax>272</ymax>
		</bndbox>
	</object>
	<object>
		<name>furuncle</name>
		<pose>Unspecified</pose>
		<truncated>0</truncated>
		<difficult>0</difficult>
		<bndbox>
			<xmin>664</xmin>
			<ymin>268</ymin>
			<xmax>712</xmax>
			<ymax>312</ymax>
		</bndbox>
	</object>
	<object>
		<name>furuncle</name>
		<pose>Unspecified</pose>
		<truncated>0</truncated>
		<difficult>0</difficult>
		<bndbox>
			<xmin>664</xmin>
			<ymin>156</ymin>
			<xmax>708</xmax>
			<ymax>196</ymax>
		</bndbox>
	</object>
	<object>
		<name>furuncle</name>
		<pose>Unspecified</pose>
		<truncated>0</truncated>
		<difficult>0</difficult>
		<bndbox>
			<xmin>716</xmin>
			<ymin>96</ymin>
			<xmax>756</xmax>
			<ymax>136</ymax>
		</bndbox>
	</object>
	<object>
		<name>furuncle</name>
		<pose>Unspecified</pose>
		<truncated>0</truncated>
		<difficult>0</difficult>
		<bndbox>
			<xmin>780</xmin>
			<ymin>112</ymin>
			<xmax>828</xmax>
			<ymax>164</ymax>
		</bndbox>
	</object>
	<object>
		<name>furuncle</name>
		<pose>Unspecified</pose>
		<truncated>0</truncated>
		<difficult>0</difficult>
		<bndbox>
			<xmin>776</xmin>
			<ymin>224</ymin>
			<xmax>816</xmax>
			<ymax>264</ymax>
		</bndbox>
	</object>
	<object>
		<name>furuncle</name>
		<pose>Unspecified</pose>
		<truncated>0</truncated>
		<difficult>0</difficult>
		<bndbox>
			<xmin>756</xmin>
			<ymin>308</ymin>
			<xmax>808</xmax>
			<ymax>364</ymax>
		</bndbox>
	</object>
	<object>
		<name>furuncle</name>
		<pose>Unspecified</pose>
		<truncated>0</truncated>
		<difficult>0</difficult>
		<bndbox>
			<xmin>756</xmin>
			<ymin>396</ymin>
			<xmax>808</xmax>
			<ymax>444</ymax>
		</bndbox>
	</object>
	<object>
		<name>furuncle</name>
		<pose>Unspecified</pose>
		<truncated>0</truncated>
		<difficult>0</difficult>
		<bndbox>
			<xmin>836</xmin>
			<ymin>228</ymin>
			<xmax>932</xmax>
			<ymax>360</ymax>
		</bndbox>
	</object>
</annotation>