<?xml version="1.0" ?><annotation>
	<folder>furuncle</folder>
	<filename>furuncle_87.jpg</filename>
	<path>C:\Users\ASUS\Desktop\images\furuncle\furuncle_87.jpg</path>
	<source>
		<database>Unknown</database>
	</source>
	<size>
		<width>336</width>
		<height>598</height>
		<depth>3</depth>
	</size>
	<segmented>0</segmented>
	<object>
		<name>furuncle</name>
		<pose>Unspecified</pose>
		<truncated>0</truncated>
		<difficult>0</difficult>
		<bndbox>
			<xmin>96</xmin>
			<ymin>202</ymin>
			<xmax>200</xmax>
			<ymax>322</ymax>
		</bndbox>
	</object>
</annotation>