<annotation>
	<folder>insect_bite</folder>
	<filename>insect_bite_44.jpg</filename>
	<path>C:\Users\fdd2013326601001\Desktop\Images\insect_bite\insect_bite_44.jpg</path>
	<source>
		<database>Unknown</database>
	</source>
	<size>
		<width>500</width>
		<height>301</height>
		<depth>3</depth>
	</size>
	<segmented>0</segmented>
	<object>
		<name>insect bite</name>
		<pose>Unspecified</pose>
		<truncated>0</truncated>
		<difficult>0</difficult>
		<bndbox>
			<xmin>106</xmin>
			<ymin>205</ymin>
			<xmax>148</xmax>
			<ymax>248</ymax>
		</bndbox>
	</object>
	<object>
		<name>insect bite</name>
		<pose>Unspecified</pose>
		<truncated>0</truncated>
		<difficult>0</difficult>
		<bndbox>
			<xmin>175</xmin>
			<ymin>189</ymin>
			<xmax>221</xmax>
			<ymax>239</ymax>
		</bndbox>
	</object>
	<object>
		<name>insect bite</name>
		<pose>Unspecified</pose>
		<truncated>0</truncated>
		<difficult>0</difficult>
		<bndbox>
			<xmin>281</xmin>
			<ymin>83</ymin>
			<xmax>325</xmax>
			<ymax>133</ymax>
		</bndbox>
	</object>
</annotation>
